spgci_qa/__init__.py
spgci_qa/agriculture_sustainability.py
spgci_qa/americas_gas.py
spgci_qa/animal_health_economics.py
spgci_qa/api_client.py
spgci_qa/arbflow.py
spgci_qa/auth.py
spgci_qa/biofuels.py
spgci_qa/chemical_assets.py
spgci_qa/chemical_outages.py
spgci_qa/chemicals_price_forecast.py
spgci_qa/chemicals_supply_demand.py
spgci_qa/config.py
spgci_qa/crop_science.py
spgci_qa/crude_supply_risk.py
spgci_qa/epf.py
spgci_qa/eugashubbalances.py
spgci_qa/ewindow_md.py
spgci_qa/exceptions.py
spgci_qa/fertilizer.py
spgci_qa/forward_curves.py
spgci_qa/fuels_and_refining.py
spgci_qa/giem.py
spgci_qa/insights.py
spgci_qa/integrated_energy_scenarios.py
spgci_qa/lng_analytics.py
spgci_qa/lng_cargo_premium.py
spgci_qa/lng_global.py
spgci_qa/lng_global_plus.py
spgci_qa/lng_market_fundamentals.py
spgci_qa/lng_netbacks.py
spgci_qa/lng_outages.py
spgci_qa/lng_weather.py
spgci_qa/market_data.py
spgci_qa/na_gas.py
spgci_qa/oil_demand.py
spgci_qa/rapid_core_validation.py
spgci_qa/rapid_dapper_validation.py
spgci_qa/refined_product_demand.py
spgci_qa/softs_short_term.py
spgci_qa/utilities.py
spgci_qa/weather.py
spgci_qa/wos.py
spgci_qa/wrd.py
spgci_qa-0.0.3.dist-info/LICENSE
spgci_qa-0.0.3.dist-info/METADATA
spgci_qa-0.0.3.dist-info/WHEEL
spgci_qa-0.0.3.dist-info/RECORD
