Metadata-Version: 2.1
Name: spgci_qa
Version: 0.0.3
Summary: SPGCI is an API Client for the S&P Commodity Insights REST API
Home-page: https://github.com/spgi-ci/spgci-python
License: Apache-2.0
Author: S&P Global Commodity Insights
Author-email: pl_api_support@spglobal.com
Requires-Python: >=3.9.0,<4.0.0
Classifier: License :: OSI Approved :: Apache Software License
Classifier: Programming Language :: Python :: 3
Classifier: Programming Language :: Python :: 3.9
Classifier: Programming Language :: Python :: 3.10
Classifier: Programming Language :: Python :: 3.11
Requires-Dist: packaging (>=24.1,<25.0)
Requires-Dist: pandas (>=1.1.5)
Requires-Dist: requests (>=2.27.1,<3.0.0)
Requires-Dist: tenacity (>=8.2.2,<9.0.0)
Requires-Dist: tqdm (>=4.64.1,<5.0.0)
Requires-Dist: typing-extensions (>=4.4.0,<5.0.0)
Project-URL: Documentation, https://developer.spglobal.com/commodityinsights/tools/notebooks
Project-URL: Repository, https://github.com/spgi-ci/spgci-python
